asyncscrapy/__init__.py
asyncscrapy/asyncdefer.py
asyncscrapy/misc.py
asyncscrapy/next_req.py
asyncscrapy/offs.py
asyncscrapy/inline/__init__.py
asyncscrapy/inline/generator.py
asyncscrapy/inline/utils.py
asyncscrapy-0.2.dist-info/METADATA
asyncscrapy-0.2.dist-info/RECORD
asyncscrapy-0.2.dist-info/WHEEL
asyncscrapy-0.2.dist-info/top_level.txt
