Metadata-Version: 2.1
Name: asyncscrapy
Version: 0.2
Summary: Miscellaneous files for using asyncio in Scrapy
Home-page: UNKNOWN
Author: Yash Sharma
Author-email: UNKNOWN
License: UNKNOWN
Platform: UNKNOWN
Classifier: Programming Language :: Python :: 3
Classifier: License :: OSI Approved :: MIT License
Classifier: Operating System :: OS Independent
